aioduck/__init__.py
aioduck/core.py
aioduck-2025.9.15.dist-info/licenses/LICENSE
aioduck-2025.9.15.dist-info/METADATA
aioduck-2025.9.15.dist-info/WHEEL
aioduck-2025.9.15.dist-info/top_level.txt
aioduck-2025.9.15.dist-info/RECORD
