Metadata-Version: 2.4
Name: aioduck
Version: 2025.9.15
Summary: Python asyncio bindings for DuckDB
Author-email: fairydream <cn.fairydream@outlook.com>
License-Expression: MIT
Project-URL: Homepage, https://github.com/cnfairydream/aioduck
Project-URL: Repository, https://github.com/cnfairydream/aioduck
Requires-Python: <4.0,>=3.11
License-File: LICENSE
Requires-Dist: polars
Requires-Dist: pyarrow
Requires-Dist: duckdb
Dynamic: license-file
